terrariumai/__init__.py
terrariumai/collective.py
terrariumai/collective_pb2.py
terrariumai/collective_pb2_grpc.py
terrariumai-0.1.10.dist-info/METADATA
terrariumai-0.1.10.dist-info/WHEEL
terrariumai-0.1.10.dist-info/top_level.txt
terrariumai-0.1.10.dist-info/RECORD
