Metadata-Version: 2.1
Name: terrariumai
Version: 0.1.10
Summary: Utility package for using Terrarium.ai
Home-page: http://github.com/terrariumai
Author: Zac Holland
Author-email: zacharyhollland@gmail.com
License: MIT
Platform: UNKNOWN
Classifier: Programming Language :: Python :: 3
Classifier: License :: OSI Approved :: MIT License
Classifier: Operating System :: OS Independent
Requires-Dist: grpcio
Requires-Dist: protobuf
